workalendar/__init__.py
workalendar/astronomy.py
workalendar/core.py
workalendar/equinoxes.json.gz
workalendar/exceptions.py
workalendar/precomputed_astronomy.py
workalendar/registry.py
workalendar/registry_tools.py
workalendar/skyfield_astronomy.py
workalendar/solar_terms.json.gz
workalendar/africa/__init__.py
workalendar/africa/algeria.py
workalendar/africa/angola.py
workalendar/africa/benin.py
workalendar/africa/ivory_coast.py
workalendar/africa/kenya.py
workalendar/africa/madagascar.py
workalendar/africa/mozambique.py
workalendar/africa/nigeria.py
workalendar/africa/sao_tome.py
workalendar/africa/south_africa.py
workalendar/america/__init__.py
workalendar/america/argentina.py
workalendar/america/barbados.py
workalendar/america/brazil.py
workalendar/america/canada.py
workalendar/america/chile.py
workalendar/america/colombia.py
workalendar/america/mexico.py
workalendar/america/panama.py
workalendar/america/paraguay.py
workalendar/asia/__init__.py
workalendar/asia/china.py
workalendar/asia/hong_kong.py
workalendar/asia/israel.py
workalendar/asia/japan.py
workalendar/asia/kazakhstan.py
workalendar/asia/malaysia.py
workalendar/asia/philippines.py
workalendar/asia/qatar.py
workalendar/asia/singapore.py
workalendar/asia/south_korea.py
workalendar/asia/taiwan.py
workalendar/europe/__init__.py
workalendar/europe/austria.py
workalendar/europe/belarus.py
workalendar/europe/belgium.py
workalendar/europe/bulgaria.py
workalendar/europe/cayman_islands.py
workalendar/europe/croatia.py
workalendar/europe/cyprus.py
workalendar/europe/czech_republic.py
workalendar/europe/denmark.py
workalendar/europe/estonia.py
workalendar/europe/european_central_bank.py
workalendar/europe/finland.py
workalendar/europe/france.py
workalendar/europe/georgia.py
workalendar/europe/germany.py
workalendar/europe/greece.py
workalendar/europe/guernsey.py
workalendar/europe/hungary.py
workalendar/europe/iceland.py
workalendar/europe/ireland.py
workalendar/europe/italy.py
workalendar/europe/latvia.py
workalendar-16.4.0.dist-info/LICENSE
workalendar-16.4.0.dist-info/METADATA
workalendar-16.4.0.dist-info/WHEEL
workalendar-16.4.0.dist-info/top_level.txt
workalendar-16.4.0.dist-info/RECORD
