Metadata-Version: 2.1
Name: workalendar
Version: 16.4.0
Summary: Worldwide holidays and working days helper and toolkit.
Home-page: https://github.com/workalendar/workalendar
Author: Bruno Bord
Author-email: bruno@jehaisleprintemps.net
License: MIT License
Platform: UNKNOWN
Classifier: Development Status :: 5 - Production/Stable
Classifier: Intended Audience :: Developers
Classifier: License :: OSI Approved :: MIT License
Classifier: Programming Language :: Python
Classifier: Programming Language :: Python :: 3
Classifier: Programming Language :: Python :: 3.6
Classifier: Programming Language :: Python :: 3.7
Classifier: Programming Language :: Python :: 3.8
Classifier: Programming Language :: Python :: 3.9
Requires-Python: >=3.6
Requires-Dist: python-dateutil
Requires-Dist: lunardate
Requires-Dist: convertdate
Requires-Dist: pyluach
Requires-Dist: tzdata ; platform_system == "Windows"
Requires-Dist: importlib-metadata ; python_version < "3.8"
Requires-Dist: backports.zoneinfo ; python_version < "3.9"
Provides-Extra: astronomy
Requires-Dist: skyfield ; extra == 'astronomy'
Requires-Dist: skyfield-data ; extra == 'astronomy'
